fastapi3_crud/__init__.py
fastapi3_crud/crud/__init__.py
fastapi3_crud/crud/fast_crud.py
fastapi3_crud/crud/helper.py
fastapi3_crud/endpoint/__init__.py
fastapi3_crud/endpoint/crud_router.py
fastapi3_crud/endpoint/endpoint_creator.py
fastapi3_crud/endpoint/helper.py
fastapi3_crud/examples/article/model.py
fastapi3_crud/examples/article/schemas.py
fastapi3_crud/examples/author/model.py
fastapi3_crud/examples/author/schemas.py
fastapi3_crud/examples/customer/model.py
fastapi3_crud/examples/customer/schemas.py
fastapi3_crud/examples/department/model.py
fastapi3_crud/examples/department/schemas.py
fastapi3_crud/examples/item/model.py
fastapi3_crud/examples/item/schemas.py
fastapi3_crud/examples/item/sqlmodel.py
fastapi3_crud/examples/mymodel/model.py
fastapi3_crud/examples/mymodel/schemas.py
fastapi3_crud/examples/order/model.py
fastapi3_crud/examples/order/schemas.py
fastapi3_crud/examples/product/model.py
fastapi3_crud/examples/product/schemas.py
fastapi3_crud/examples/profile/model.py
fastapi3_crud/examples/profile/schemas.py
fastapi3_crud/examples/story/model.py
fastapi3_crud/examples/story/schemas.py
fastapi3_crud/examples/task/model.py
fastapi3_crud/examples/task/schemas.py
fastapi3_crud/examples/tier/model.py
fastapi3_crud/examples/tier/schemas.py
fastapi3_crud/examples/user/model.py
fastapi3_crud/examples/user/schemas.py
fastapi3_crud/exceptions/__init__.py
fastapi3_crud/exceptions/http_exceptions.py
fastapi3_crud/paginated/__init__.py
fastapi3_crud/paginated/helper.py
fastapi3_crud/paginated/response.py
fastapi3_crud/paginated/schemas.py
fastapi3_crud/py.typed
fastapi3_crud/types.py
fastapi3_crud-0.1.1.dist-info/METADATA
fastapi3_crud-0.1.1.dist-info/WHEEL
fastapi3_crud-0.1.1.dist-info/RECORD
